{
  "CHANNEL": "Kênh",
  "CHANNELS": "Các kênh",
  "CHANNEL_TYPE": "Loại kênh",
  "CHANNEL_TYPES": {
    "ANNOUNCEMENT_THREAD": "Announcement thread",
    "GUILD_ANNOUNCEMENT": "Announcement channel",
    "GUILD_CATEGORY": "Danh mục",
    "GUILD_FORUM": "Forum channel",
    "GUILD_STAGE_VOICE": "Kênh sân khấu",
    "GUILD_TEXT": "Kênh nhắn tin",
    "GUILD_VOICE": "Kênh thoại",
    "PRIVATE_THREAD": "Private thread",
    "PUBLIC_THREAD": "Public thread",
    "GUILD_RULES": "Kênh về luật lệ",
    "GUILD_DISCORD_ANNOUNCEMENT": "Discord announcement channel",
    "GUILD_AFK": "Kênh AFK",
    "UNKNOWN": "Loại kênh không xác định"
  },
  "CHANNEL_POSITION": "Vị trí kênh",
  "CATEGORY": "Danh mục",
  "WITHOUT_CATEGORY": "Không có danh mục",
  "UNKNOWN_CATEGORY": "Danh mục không xác định",
  "NSFW": "NSFW (18+)",
  "COOLDOWN": "Thời gian hồi",
  "TOPIC": "Chủ đề",
  "THREAD": "Chủ đề",
  "DISCORD_DEFAULT_TOPIC": "Không có chủ đề",
  "CHANNEL_REGION": "Khu vực của kênh",
  "AUTOMATIC_REGION": "Khu vực tự động",
  "CHANNEL_BITRATE": "Bitrate của kênh",
  "UNKNOWN_BITRATE": "Bitrate không xác định",
  "CHANNEL_USER_LIMIT": "Giới hạn người dùng của kênh",
  "WITHOUT_USER_LIMIT": "Không có giới hạn người dùng",
  "TIME_TO_ARCHIVING": "Thời gian để xoá",
  "THREAD_MEMBER_COUNTER": "Đếm số người dùng trong một chủ đề",
  "THREAD_MESSAGE_COUNTER": "Đếm số tin nhắn trong một chủ đề",
  "CHANNEL_LOCKED_TRUE": "Kênh này đang bị khoá",
  "CHANNEL_LOCKED_FALSE": "Kênh này không bị khoá",
  "CHANNEL_ARCHIVED_TRUE": "Kênh đã đã được lưu trữ",
  "CHANNEL_ARCHIVED_FALSE": "Kênh này chưa được lưu trữ"
}
