{
  "LOADING_ACTION": "请等待，等待所请求的行动加载。",
  "MESSAGE": {
    "MANAGE_THIS_MESSAGE": {
      "PIN_MESSAGE_TITLE": "销号信息",
      "PIN_MESSAGE_DESCRIPTION": "在这个频道上钉上这个消息。",
      "UNPIN_MESSAGE_TITLE": "撤下信息",
      "UNPIN_MESSAGE_DESCRIPTION": "从这个频道取消这个消息。"
    }
  },
  "USER": {
    "MISCELLANEOUS_ACTIONS": {
      "SHOW_USER_AVATAR_TITLE": "显示用户头像",
      "SHOW_USER_AVATAR_DESCRIPTION": "显示该用户的头像。",
      "SHOW_USER_PROFILE_TITLE": "显示用户资料",
      "SHOW_USER_PROFILE_DESCRIPTION": "显示该用户的简介。"
    },
    "MODERATE_THIS_USER": {
      "PERMANENTLY_BAN_THIS_USER_TITLE": "永久禁止该用户",
      "PERMANENTLY_BAN_THIS_USER_DESCRIPTION": "永久禁止该用户进入服务器。",
      "SHOW_USER_HISTORY_TITLE": "显示用户的历史",
      "SHOW_USER_HISTORY_DESCRIPTION": "显示用户的制裁历史。",
      "KICK_THIS_USER_TITLE": "踢掉这个用户",
      "KICK_THIS_USER_DESCRIPTION": "把这个用户从服务器上踢出去。",
      "PERMANENTLY_MUTE_THIS_USER_TITLE": "永久性地使该用户静音",
      "PERMANENTLY_MUTE_THIS_USER_DESCRIPTION": "将该用户从服务器上永久静音。",
      "SOFTBAN_THIS_USER_TITLE": "软禁该用户",
      "SOFTBAN_THIS_USER_DESCRIPTION": "从服务器上软禁该用户。",
      "TEMPORARILY_BAN_THIS_USER_TITLE": "暂时禁止该用户",
      "TEMPORARILY_BAN_THIS_USER_DESCRIPTION": "暂时禁止该用户进入服务器。",
      "TEMPORARILY_MUTE_THIS_USER_TITLE": "暂时静音该用户",
      "TEMPORARILY_MUTE_THIS_USER_DESCRIPTION": "暂时将该用户从服务器上静音。",
      "UNBAN_THIS_USER_TITLE": "解除对该用户的禁令",
      "UNBAN_THIS_USER_DESCRIPTION": "将该用户从服务器上解禁。",
      "UNMUTE_THIS_USER_TITLE": "取消该用户的静音",
      "UNMUTE_THIS_USER_DESCRIPTION": "从服务器上取消该用户的静音。",
      "UNWARN_THIS_USER_TITLE": "取消对该用户的警告",
      "UNWARN_THIS_USER_DESCRIPTION": "从服务器上取消对该用户的警告。",
      "WARN_THIS_USER_TITLE": "向该用户发出警告",
      "WARN_THIS_USER_DESCRIPTION": "从服务器上警告这个用户。",
      "TIMEOUT_THIS_USER_TITLE": "Timeout this user",
      "TIMEOUT_THIS_USER_DESCRIPTION": "Timeout this user from the server.",
      "UNTIMEOUT_THIS_USER_TITLE": "Untimeout this user",
      "UNTIMEOUT_THIS_USER_DESCRIPTION": "Untimeout this user from the server."
    }
  }
}