{
  "description": "Eliminar el silencio de un usuario.",
  "arguments": {
    "user": {
      "name": "usuario",
      "description": "Usuario al que quieres eliminar el silencio."
    },
    "reason": {
      "name": "raz贸n",
      "description": "Raz贸n para eliminar el silencio."
    },
    "silent": {
      "name": "silencioso",
      "description": "Especifica si quieres que la sanci贸n no sea notificada para el usuario."
    },
    "force": {
      "name": "forzar",
      "description": "Forzar la eliminaci贸n del silencio."
    }
  }
}