{
  "COOLDOWN": {
    "COMPLETED": "**{{time}}** adresini **[#{{channel.name}}]({{url}})** kanalında bekleme süresi olarak ayarladınız."
  },
  "MESSAGES": {
    "PIN": {
      "COMPLETED": "**[{{message.id}}]({{message.url}})** mesajını **[#{{channel.name}}]({{url}})** kanalına sabitlediniz."
    },
    "PURGE": {
      "COMPLETED": "**{{messages}}** mesajlarını **[#{{channel.name}}]({{url}})** ({{channel.id}}) kanalından temizlediniz."
    },
    "UNPIN": {
      "COMPLETED": "**[#{{channel.name}}]({{url}})** kanalındaki **[{{message.id}}]({{message.url}})** mesajının sabitlemesini kaldırdınız."
    }
  },
  "NSFW": {
    "COMPLETED": "**[#{{channel.name}}]({{url}})** ({{channel.id}}) kanalında {{action}} NSFW moduna sahipsiniz."
  }
}