{
  "CREATE_INSTANT_INVITE": "Crear una invitació",
  "KICK_MEMBERS": "Expulsar membres",
  "BAN_MEMBERS": "Prohibir membres",
  "ADMINISTRATOR": "Administrador",
  "MANAGE_CHANNELS": "Gestionar canals",
  "MANAGE_GUILD": "Gestionar servidor",
  "ADD_REACTIONS": "Afegir reaccions",
  "VIEW_AUDIT_LOG": "Veure el registre d'auditoria",
  "PRIORITY_SPEAKER": "Prioritat de paraula",
  "STREAM": "Vídeo",
  "VIEW_CHANNEL": "Veure canals",
  "SEND_MESSAGES": "Enviar missatges",
  "SEND_TTS_MESSAGES": "Enviar missatges de text a veu",
  "MANAGE_MESSAGES": "Gestionar missatges",
  "EMBED_LINKS": "Inserir enllaços",
  "ATTACH_FILES": "Adjuntar arxius",
  "READ_MESSAGE_HISTORY": "Llegir l'historial de missatges",
  "MENTION_EVERYONE": "Mencionar @everyone, @here i tots els rols",
  "USE_EXTERNAL_EMOJIS": "Utilitzar emojis externs",
  "VIEW_GUILD_INSIGHTS": "Veure informació del servidor",
  "CONNECT": "Connectar",
  "SPEAK": "Parlar",
  "MUTE_MEMBERS": "Silenciar membres",
  "DEAFEN_MEMBERS": "Ensordir membres",
  "MOVE_MEMBERS": "Moure membres",
  "USE_VAD": "Utilitzar activitat de veu",
  "CHANGE_NICKNAME": "Canviar sobrenom",
  "MANAGE_NICKNAMES": "Gestionar sobrenoms",
  "MANAGE_ROLES": "Gestionar rols",
  "MANAGE_WEBHOOKS": "Gestionar \"webhooks\"",
  "MANAGE_GUILD_EXPRESSIONS": "Gestionar expressions",
  "USE_APPLICATION_COMMANDS": "Utilitzar ordres d'aplicacions",
  "REQUEST_TO_SPEAK": "Sol·licitar per parlar",
  "MANAGE_EVENTS": "Gestionar esdeveniments",
  "MANAGE_THREADS": "Gestionar fils",
  "CREATE_PUBLIC_THREADS": "Crear fils públics",
  "CREATE_PRIVATE_THREADS": "Crear fils privats",
  "USE_EXTERNAL_STICKERS": "Utilitzar adhesius externs",
  "SEND_MESSAGES_IN_THREADS": "Enviar missatges en fils",
  "START_EMBEDDED_ACTIVITIES": "Utilitzar activitats",
  "MODERATE_MEMBERS": "Aïllar temporalment a membres",
  "VIEW_CREATOR_MONETIZATION_ANALYTICS": "Veure anàlisis de monetització de creadors",
  "USE_SOUNDBOARD": "Utilitzar panels de sons",
  "USE_EXTERNAL_SOUNDS": "Utilitzar sons externs",
  "SEND_VOICE_MESSAGES": "Enviar missatges de veu"
}