{
  "description": "Envoyez un fond d'écran aléatoire de Genshin Impact.",
  "subcommands": {
    "desktop": {
      "description": "Obtenez un fond d'écran aléatoire."
    },
    "mobile": {
      "description": "Obtenez un fond d'écran mobile aléatoire."
    },
    "random": {
      "description": "Obtenez des fonds d'écran aléatoires entre l'ordinateur et le mobile."
    }
  },
  "subcommand_groups": {
    "cards": {
      "description": "Obtenez un fond d'écran aléatoire.",
      "subcommands": {
        "characters": {
          "description": "Obtenez une carte de personnage au hasard."
        },
        "equipments": {
          "description": "Obtenez une carte d'équipement aléatoire."
        },
        "events": {
          "description": "Obtenez une carte d'évènement aléatoire."
        },
        "supports": {
          "description": "Obtenez une carte de soutien aléatoire."
        }
      }
    }
  }
}
